composer/__init__.py
composer/__main__.py
composer/_version.py
composer/py.typed
composer/algorithms/__init__.py
composer/algorithms/warnings.py
composer/algorithms/alibi/__init__.py
composer/algorithms/alibi/alibi.py
composer/algorithms/alibi/metadata.json
composer/algorithms/alibi/attention_surgery_functions/__init__.py
composer/algorithms/alibi/attention_surgery_functions/_bert.py
composer/algorithms/alibi/attention_surgery_functions/_gpt2.py
composer/algorithms/alibi/attention_surgery_functions/utils.py
composer/algorithms/augmix/__init__.py
composer/algorithms/augmix/augmix.py
composer/algorithms/augmix/metadata.json
composer/algorithms/blurpool/__init__.py
composer/algorithms/blurpool/blurpool.py
composer/algorithms/blurpool/blurpool_layers.py
composer/algorithms/blurpool/metadata.json
composer/algorithms/channels_last/__init__.py
composer/algorithms/channels_last/channels_last.py
composer/algorithms/channels_last/metadata.json
composer/algorithms/colout/__init__.py
composer/algorithms/colout/colout.py
composer/algorithms/colout/metadata.json
composer/algorithms/cutmix/__init__.py
composer/algorithms/cutmix/cutmix.py
composer/algorithms/cutmix/metadata.json
composer/algorithms/cutout/__init__.py
composer/algorithms/cutout/cutout.py
composer/algorithms/cutout/metadata.json
composer/algorithms/ema/__init__.py
composer/algorithms/ema/ema.py
composer/algorithms/ema/metadata.json
composer/algorithms/factorize/__init__.py
composer/algorithms/factorize/factorize.py
composer/algorithms/factorize/factorize_core.py
composer/algorithms/factorize/factorize_modules.py
composer/algorithms/factorize/metadata.json
composer/algorithms/gated_linear_units/__init__.py
composer/algorithms/gated_linear_units/gated_linear_unit_layers.py
composer/algorithms/gated_linear_units/gated_linear_units.py
composer/algorithms/gated_linear_units/metadata.json
composer/algorithms/ghost_batchnorm/__init__.py
composer/algorithms/ghost_batchnorm/ghost_batchnorm.py
mosaicml-0.32.1.dist-info/licenses/LICENSE
mosaicml-0.32.1.dist-info/METADATA
mosaicml-0.32.1.dist-info/WHEEL
mosaicml-0.32.1.dist-info/dependency_links.txt
mosaicml-0.32.1.dist-info/entry_points.txt
mosaicml-0.32.1.dist-info/top_level.txt
mosaicml-0.32.1.dist-info/RECORD
