Metadata-Version: 2.4
Name: mosaicml
Version: 0.32.1
Summary: Composer is a PyTorch library that enables you to train neural networks faster, at lower cost, and to higher accuracy.
Home-page: https://github.com/mosaicml/composer
Author: MosaicML
Author-email: team@mosaicml.com
Classifier: Programming Language :: Python :: 3
Classifier: Programming Language :: Python :: 3.10
Classifier: Programming Language :: Python :: 3.11
Classifier: Programming Language :: Python :: 3.12
Requires-Python: >=3.10
License-File: LICENSE
Requires-Dist: pyyaml<7,>=6.0
Requires-Dist: tqdm<5,>=4.62.3
Requires-Dist: torchmetrics<1.7.5,>=1.0
Requires-Dist: torch_optimizer<0.4,>=0.3.0
Requires-Dist: torchvision<0.22.1,>=0.21.0
Requires-Dist: torch<2.7.1,>=2.6.0
Requires-Dist: requests<3,>=2.26.0
Requires-Dist: numpy<2.3.0,>=1.21.5
Requires-Dist: psutil<8,>=5.8.0
Requires-Dist: coolname<3,>=1.1.0
Requires-Dist: tabulate==0.9.0
Requires-Dist: py-cpuinfo<10,>=8.0.0
Requires-Dist: packaging<25.1,>=21.3.0
Requires-Dist: importlib-metadata<9,>=5.0.0
Requires-Dist: mosaicml-cli<0.8,>=0.5.25
Requires-Dist: pillow<12,>=10.3.0
Provides-Extra: base
Provides-Extra: dev
Requires-Dist: custom_inherit==2.4.1; extra == "dev"
Requires-Dist: junitparser==4.0.2; extra == "dev"
Requires-Dist: coverage[toml]<8,>=7.8.0; extra == "dev"
Requires-Dist: fasteners==0.18; extra == "dev"
Requires-Dist: pytest==7.4.4; extra == "dev"
Requires-Dist: ipython==8.37.0; extra == "dev"
Requires-Dist: ipykernel==6.29.5; extra == "dev"
Requires-Dist: jupyter==1.1.1; extra == "dev"
Requires-Dist: yamllint==1.37.1; extra == "dev"
Requires-Dist: recommonmark==0.7.1; extra == "dev"
Requires-Dist: sphinx==4.4.0; extra == "dev"
Requires-Dist: pre-commit<5,>=3.4.0; extra == "dev"
Requires-Dist: docutils==0.17.1; extra == "dev"
Requires-Dist: sphinx_markdown_tables==0.0.17; extra == "dev"
Requires-Dist: sphinx-argparse==0.4.0; extra == "dev"
Requires-Dist: sphinxcontrib.katex==0.9.11; extra == "dev"
Requires-Dist: sphinxcontrib-applehelp==1.0.0; extra == "dev"
Requires-Dist: sphinxcontrib-devhelp==1.0.0; extra == "dev"
Requires-Dist: sphinxcontrib-htmlhelp==2.0.0; extra == "dev"
Requires-Dist: sphinxcontrib-serializinghtml==1.1.5; extra == "dev"
Requires-Dist: sphinxcontrib-qthelp==1.0.0; extra == "dev"
Requires-Dist: sphinxext.opengraph==0.9.1; extra == "dev"
Requires-Dist: sphinxemoji==0.2.0; extra == "dev"
Requires-Dist: furo==2022.9.29; extra == "dev"
Requires-Dist: sphinx-copybutton==0.5.2; extra == "dev"
Requires-Dist: testbook==0.4.2; extra == "dev"
Requires-Dist: myst-parser==0.16.1; extra == "dev"
Requires-Dist: sphinx_panels==0.6.0; extra == "dev"
Requires-Dist: sphinxcontrib-images==0.9.4; extra == "dev"
Requires-Dist: pytest_codeblocks==0.17.0; extra == "dev"
Requires-Dist: traitlets==5.14.3; extra == "dev"
Requires-Dist: nbsphinx==0.9.1; extra == "dev"
Requires-Dist: pandoc==2.4; extra == "dev"
Requires-Dist: pypandoc==1.15; extra == "dev"
Requires-Dist: GitPython==3.1.44; extra == "dev"
Requires-Dist: moto[s3]<6,>=5.0.1; extra == "dev"
Requires-Dist: mock-ssh-server==0.9.1; extra == "dev"
Requires-Dist: cryptography==44.0.3; extra == "dev"
Requires-Dist: pytest-httpserver<1.2,>=1.0.4; extra == "dev"
Requires-Dist: setuptools<79.0.0; extra == "dev"
Provides-Extra: system-metrics-monitor
Requires-Dist: pynvml<12,>=11.5.0; extra == "system-metrics-monitor"
Provides-Extra: slack
Requires-Dist: slack_sdk<4,>=3.19.5; extra == "slack"
Provides-Extra: wandb
Requires-Dist: wandb<0.19,>=0.13.2; extra == "wandb"
Provides-Extra: comet-ml
Requires-Dist: comet_ml<4.0.0,>=3.31.12; extra == "comet-ml"
Provides-Extra: neptune
Requires-Dist: neptune<2.0.0,>=1.6.2; extra == "neptune"
Provides-Extra: tensorboard
Requires-Dist: tensorboard<3.0.0,>=2.9.1; extra == "tensorboard"
Provides-Extra: coco
Requires-Dist: pycocotools<3,>=2.0.4; extra == "coco"
Provides-Extra: nlp
Requires-Dist: transformers!=4.34.0,<4.54,>=4.11; extra == "nlp"
Requires-Dist: datasets<5,>=2.4; extra == "nlp"
Requires-Dist: huggingface-hub<0.34,>=0.21.2; extra == "nlp"
Provides-Extra: peft
Requires-Dist: peft<0.17,>=0.10.0; extra == "peft"
Provides-Extra: sentencepiece
Requires-Dist: protobuf<5.30; extra == "sentencepiece"
Requires-Dist: sentencepiece==0.2.0; extra == "sentencepiece"
Provides-Extra: mlperf
Requires-Dist: py-cpuinfo<10,>=8.0.0; extra == "mlperf"
Provides-Extra: streaming
Requires-Dist: mosaicml-streaming<1.0; extra == "streaming"
Requires-Dist: boto3<2,>=1.21.45; extra == "streaming"
Requires-Dist: paramiko<4,>=3.4.0; extra == "streaming"
Provides-Extra: libcloud
Requires-Dist: apache-libcloud<4,>=3.3.1; extra == "libcloud"
Provides-Extra: oci
Requires-Dist: oci<3.0.0,>=2.88.2; extra == "oci"
Provides-Extra: gcs
Requires-Dist: google-cloud-storage<4.0,>=2.0.0; extra == "gcs"
Provides-Extra: onnx
Requires-Dist: onnx<2,>=1.12.0; extra == "onnx"
Requires-Dist: onnxruntime<2,>=1.12.1; extra == "onnx"
Provides-Extra: mlflow
Requires-Dist: mlflow<3.0,>=2.14.1; extra == "mlflow"
Requires-Dist: databricks-sdk<1,>=0.50.0; extra == "mlflow"
Requires-Dist: pynvml<12,>=11.5.0; extra == "mlflow"
Provides-Extra: pandas
Requires-Dist: pandas<3.0,>=2.0.0; extra == "pandas"
Provides-Extra: databricks
Requires-Dist: databricks-sdk<1,>=0.50.0; extra == "databricks"
Provides-Extra: all
Requires-Dist: ipython==8.37.0; extra == "all"
Requires-Dist: pypandoc==1.15; extra == "all"
Requires-Dist: sphinx_markdown_tables==0.0.17; extra == "all"
Requires-Dist: pynvml<12,>=11.5.0; extra == "all"
Requires-Dist: fasteners==0.18; extra == "all"
Requires-Dist: ipykernel==6.29.5; extra == "all"
Requires-Dist: docutils==0.17.1; extra == "all"
Requires-Dist: furo==2022.9.29; extra == "all"
Requires-Dist: sphinx_panels==0.6.0; extra == "all"
Requires-Dist: sphinxcontrib-serializinghtml==1.1.5; extra == "all"
Requires-Dist: databricks-sdk<1,>=0.50.0; extra == "all"
Requires-Dist: cryptography==44.0.3; extra == "all"
Requires-Dist: apache-libcloud<4,>=3.3.1; extra == "all"
Requires-Dist: pre-commit<5,>=3.4.0; extra == "all"
Requires-Dist: sphinx==4.4.0; extra == "all"
Requires-Dist: py-cpuinfo<10,>=8.0.0; extra == "all"
Requires-Dist: tensorboard<3.0.0,>=2.9.1; extra == "all"
Requires-Dist: sentencepiece==0.2.0; extra == "all"
Requires-Dist: mosaicml-streaming<1.0; extra == "all"
Requires-Dist: onnx<2,>=1.12.0; extra == "all"
Requires-Dist: yamllint==1.37.1; extra == "all"
Requires-Dist: mock-ssh-server==0.9.1; extra == "all"
Requires-Dist: boto3<2,>=1.21.45; extra == "all"
Requires-Dist: junitparser==4.0.2; extra == "all"
Requires-Dist: pytest==7.4.4; extra == "all"
Requires-Dist: onnxruntime<2,>=1.12.1; extra == "all"
Requires-Dist: wandb<0.19,>=0.13.2; extra == "all"
Requires-Dist: sphinxcontrib-htmlhelp==2.0.0; extra == "all"
Requires-Dist: pytest_codeblocks==0.17.0; extra == "all"
Requires-Dist: pycocotools<3,>=2.0.4; extra == "all"
Requires-Dist: moto[s3]<6,>=5.0.1; extra == "all"
Requires-Dist: sphinxcontrib-applehelp==1.0.0; extra == "all"
Requires-Dist: GitPython==3.1.44; extra == "all"
Requires-Dist: coverage[toml]<8,>=7.8.0; extra == "all"
Requires-Dist: neptune<2.0.0,>=1.6.2; extra == "all"
Requires-Dist: peft<0.17,>=0.10.0; extra == "all"
Requires-Dist: pandoc==2.4; extra == "all"
Requires-Dist: sphinxext.opengraph==0.9.1; extra == "all"
Requires-Dist: pytest-httpserver<1.2,>=1.0.4; extra == "all"
Requires-Dist: paramiko<4,>=3.4.0; extra == "all"
Requires-Dist: slack_sdk<4,>=3.19.5; extra == "all"
Requires-Dist: testbook==0.4.2; extra == "all"
Requires-Dist: setuptools<79.0.0; extra == "all"
Requires-Dist: huggingface-hub<0.34,>=0.21.2; extra == "all"
Requires-Dist: pandas<3.0,>=2.0.0; extra == "all"
Requires-Dist: sphinxcontrib-images==0.9.4; extra == "all"
Requires-Dist: sphinx-argparse==0.4.0; extra == "all"
Requires-Dist: sphinxcontrib.katex==0.9.11; extra == "all"
Requires-Dist: recommonmark==0.7.1; extra == "all"
Requires-Dist: jupyter==1.1.1; extra == "all"
Requires-Dist: sphinxemoji==0.2.0; extra == "all"
Requires-Dist: nbsphinx==0.9.1; extra == "all"
Requires-Dist: sphinx-copybutton==0.5.2; extra == "all"
Requires-Dist: datasets<5,>=2.4; extra == "all"
Requires-Dist: oci<3.0.0,>=2.88.2; extra == "all"
Requires-Dist: protobuf<5.30; extra == "all"
Requires-Dist: sphinxcontrib-devhelp==1.0.0; extra == "all"
Requires-Dist: custom_inherit==2.4.1; extra == "all"
Requires-Dist: comet_ml<4.0.0,>=3.31.12; extra == "all"
Requires-Dist: transformers!=4.34.0,<4.54,>=4.11; extra == "all"
Requires-Dist: mlflow<3.0,>=2.14.1; extra == "all"
Requires-Dist: traitlets==5.14.3; extra == "all"
Requires-Dist: google-cloud-storage<4.0,>=2.0.0; extra == "all"
Requires-Dist: myst-parser==0.16.1; extra == "all"
Requires-Dist: sphinxcontrib-qthelp==1.0.0; extra == "all"
Dynamic: author
Dynamic: author-email
Dynamic: classifier
Dynamic: description
Dynamic: description-content-type
Dynamic: home-page
Dynamic: license-file
Dynamic: provides-extra
Dynamic: requires-dist
Dynamic: requires-python
Dynamic: summary
